gray_formatter/__init__.py
gray_formatter/__main__.py
gray_formatter/_ast_helpers.py
gray_formatter/_data.py
gray_formatter/_main.py
gray_formatter/_token_helpers.py
gray_formatter/quotes_rewriter.py
gray_formatter/_plugins/__init__.py
gray_formatter/_plugins/_with.py
gray_formatter/_plugins/calls.py
gray_formatter/_plugins/classes.py
gray_formatter/_plugins/functions.py
gray_formatter/_plugins/imports.py
gray_formatter/_plugins/literals.py
gray_formatter/_plugins/match.py
gray_formatter-3.0.10.dist-info/LICENSE
gray_formatter-3.0.10.dist-info/METADATA
gray_formatter-3.0.10.dist-info/WHEEL
gray_formatter-3.0.10.dist-info/entry_points.txt
gray_formatter-3.0.10.dist-info/top_level.txt
gray_formatter-3.0.10.dist-info/RECORD
